pywe_pay/__init__.py
pywe_pay/base.py
pywe_pay/compat.py
pywe_pay/pay.py
pywe_pay/utils.py
pywe_pay/api/__init__.py
pywe_pay/api/bill.py
pywe_pay/api/coupon.py
pywe_pay/api/jsapi.py
pywe_pay/api/micropay.py
pywe_pay/api/order.py
pywe_pay/api/redpack.py
pywe_pay/api/refund.py
pywe_pay/api/tools.py
pywe_pay/api/transfer.py
pywe_pay-1.0.14.dist-info/METADATA
pywe_pay-1.0.14.dist-info/WHEEL
pywe_pay-1.0.14.dist-info/top_level.txt
pywe_pay-1.0.14.dist-info/RECORD
